Workbook

Sheet Итоги
A1: Игровой ПК по подписке: юнит-экономика одного ПК
A2: Все цифры считаются из листа «Допущения». Меняйте синие ячейки там.
A4: Показатель | B4: Значение | C4: Комментарий
A5: Стоимость сборки в рознице (DNS) | B5: =Допущения!$B$5 | C5: Бюджетная сборка AM4 + RTX 5050
A6: Вложения в один ПК | B6: =Допущения!$B$23 | C6: Закупка со скидкой + сборка
A7: Цена подписки | B7: =Допущения!$B$8 | C7: В месяц
A8: Чистый денежный поток в месяц | B8: =Допущения!$B$29 | C8: После налога, эквайринга, ремонта, CAC
A9: Маржа денежного потока | B9: =Допущения!$B$30
A10: Срок окупаемости | B10: =IFERROR(Допущения!$B$23/Допущения!$B$29,"не окупается") | C10: Без учёта продажи ПК в конце
A11: NPV одного ПК за 36 мес | B11: =SUM('Денежный поток'!I5:I41) | C11: Дисконт по ставке из допущений; > 0 значит бизнес зарабатывает больше стоимости денег
A12: IRR, годовых | B12: =IFERROR((1+IRR('Денежный поток'!G5:G41))^12-1,"-") | C12: Сравните со ставкой финансирования
A13: Суммарная прибыль с ПК за 36 мес | B13: ='Денежный поток'!H41 | C13: Без дисконтирования

Sheet Цены
A1: Бюджетная игровая сборка (AM4), самые дешёвые позиции в DNS
A2: Источник: data/raw/local_2026-09-24.csv, сбор src/collect_local.py, 24.09.2026, Москва
A4: Компонент | B4: Позиция | C4: Цена, ₽
A5: Процессор | B5: AMD Ryzen 5 5600 OEM | C5: 11999
A6: Видеокарта | B6: MSI GeForce RTX 5050 SHADOW 2X OC 8 ГБ | C6: 39499
A7: Оперативная память | B7: Digma 16 ГБ DDR4-3200 | C7: 12599
A8: SSD | B8: DEXP C100 1 ТБ SATA | C8: 10999
A9: Материнская плата | B9: MSI PRO A520M-S | C9: 4599
A10: Кулер | B10: ID-COOLING SE-902-SD V3 | C10: 850
A11: Блок питания | B11: Formula ECO-500W | C11: 2299
A12: Корпус | B12: ExeGate BAA-109U2 | C12: 1450
A13: Итого | C13: =SUM(C5:C12)
A14: Память и SSD, доля | C14: =(C7+C8)/C13
A15: Видеокарта, доля | C15: =C6/C13

Sheet Допущения
A1: Допущения модели: игровой ПК по подписке
A2: Синие ячейки — входные данные, их можно менять. Жёлтые — ключевые рычаги. Зелёные — ссылки на другие листы. Всё остальное считается формулами.
A4: Параметр | B4: Значение | C4: Ед. | D4: Источник / логика
A5: Стоимость сборки в рознице | B5: =Цены!$C$13 | C5: ₽ | D5: Лист «Цены»: DNS, 24.09.2026
A6: Скидка при закупке у дистрибьютора | B6: 0.08 | C6: % | D6: Допущение: оптовая цена на 5–10% ниже розничной
A7: Сборка, тест, упаковка | B7: 2500 | C7: ₽ / ПК | D7: Допущение: ~1 час сборщика + упаковка
A8: Цена подписки | B8: 4990 | C8: ₽ / мес | D8: Решение. Ориентиры: клуб 1 570–1 900 ₽/мес на гостя (АРКИ, IV кв. 2025); Aura-Rent, ПК уровня RTX 4060 — 13 000 ₽/мес (краткосрочная аренда)
A9: Простой ПК между клиентами | B9: 0.1 | C9: % времени | D9: Допущение: доставка, чистка, проверка, поиск нового клиента
A10: Средняя длительность подписки | B10: 18 | C10: мес | D10: Допущение: минимальный срок 12 мес, часть клиентов продлевает
A11: Стоимость привлечения клиента (CAC) | B11: 4000 | C11: ₽ / договор | D11: Допущение: таргет и блогеры в игровых нишах
A12: Доставка и забор ПК | B12: 2000 | C12: ₽ / договор | D12: Допущение: курьер в обе стороны по городу
A13: Эквайринг | B13: 0.025 | C13: % выручки | D13: Типовая ставка интернет-эквайринга
A14: Налог (УСН «доходы») | B14: 0.06 | C14: % выручки | D14: НК РФ, ст. 346.20
A15: Ремонт и поддержка | B15: 0.06 | C15: % стоимости ПК в год | D15: Допущение: гарантийные замены, термопаста, поддержка
A16: Потери (невозврат, порча) | B16: 0.03 | C16: % парка в год | D16: Допущение: частично покрывается скорингом и договором
A17: Срок службы ПК в парке | B17: 36 | C17: мес | D17: Допущение: после 3 лет ПК продаётся на вторичном рынке
A18: Остаточная стоимость ПК через 36 мес | B18: 0.35 | C18: % цены закупки | D18: Допущение. Дорогая память поднимает и цены б/у, это работает в плюс
A19: Стоимость денег | B19: =0.14+0.04 | C19: % годовых | D19: Ключевая ставка ЦБ 14% на 23.09.2026 (cbr.ru) + 4 п.п. банковская маржа
A21: Расчётные величины
A22: Закупка комплектующих | B22: =Допущения!$B$5*(1-Допущения!$B$6)
A23: Вложения в один ПК (закупка + сборка) | B23: =Допущения!$B$5*(1-Допущения!$B$6)+Допущения!$B$7
A24: Ставка в месяц | B24: =(1+Допущения!$B$19)^(1/12)-1
A25: Выручка в месяц с учётом простоя | B25: =Допущения!$B$8*(1-Допущения!$B$9)
A26: Эквайринг и налог в месяц | B26: =B25*(Допущения!$B$13+Допущения!$B$14)
A27: Ремонт и потери в месяц | B27: =B22*(Допущения!$B$15+Допущения!$B$16)/12
A28: CAC и доставка в месяц (на договор / его длительность) | B28: =(Допущения!$B$11+Допущения!$B$12)/Допущения!$B$10*(1-Допущения!$B$9)
A29: Чистый денежный поток в месяц | B29: =B25-B26-B27-B28
A30: Маржа денежного потока | B30: =B29/B25

Sheet Денежный поток
A1: Денежный поток одного ПК за срок службы
A2: Месяц 0 — закупка и сборка. В последний месяц ПК продаётся по остаточной стоимости.
A4: Месяц | B4: Выручка | C4: Эквайринг и налог | D4: Ремонт и потери | E4: CAC и доставка | F4: Вложения / продажа | G4: Денежный поток | H4: Накопленный | I4: Дисконтированный
A5: 0 | B5: 0 | C5: 0 | D5: 0 | E5: 0 | F5: =-Допущения!$B$23 | G5: =SUM(B5:F5) | H5: =G5 | I5: =G5/(1+Допущения!$B$24)^A5
A6: 1 | B6: =Допущения!$B$25 | C6: =-Допущения!$B$26 | D6: =-Допущения!$B$27 | E6: =-Допущения!$B$28 | F6: =IF(A6=Допущения!$B$17,Допущения!$B$18*Допущения!$B$22,0) | G6: =SUM(B6:F6) | H6: =H5+G6 | I6: =G6/(1+Допущения!$B$24)^A6
A7: 2 | B7: =Допущения!$B$25 | C7: =-Допущения!$B$26 | D7: =-Допущения!$B$27 | E7: =-Допущения!$B$28 | F7: =IF(A7=Допущения!$B$17,Допущения!$B$18*Допущения!$B$22,0) | G7: =SUM(B7:F7) | H7: =H6+G7 | I7: =G7/(1+Допущения!$B$24)^A7
A8: 3 | B8: =Допущения!$B$25 | C8: =-Допущения!$B$26 | D8: =-Допущения!$B$27 | E8: =-Допущения!$B$28 | F8: =IF(A8=Допущения!$B$17,Допущения!$B$18*Допущения!$B$22,0) | G8: =SUM(B8:F8) | H8: =H7+G8 | I8: =G8/(1+Допущения!$B$24)^A8
A9: 4 | B9: =Допущения!$B$25 | C9: =-Допущения!$B$26 | D9: =-Допущения!$B$27 | E9: =-Допущения!$B$28 | F9: =IF(A9=Допущения!$B$17,Допущения!$B$18*Допущения!$B$22,0) | G9: =SUM(B9:F9) | H9: =H8+G9 | I9: =G9/(1+Допущения!$B$24)^A9
A10: 5 | B10: =Допущения!$B$25 | C10: =-Допущения!$B$26 | D10: =-Допущения!$B$27 | E10: =-Допущения!$B$28 | F10: =IF(A10=Допущения!$B$17,Допущения!$B$18*Допущения!$B$22,0) | G10: =SUM(B10:F10) | H10: =H9+G10 | I10: =G10/(1+Допущения!$B$24)^A10
A11: 6 | B11: =Допущения!$B$25 | C11: =-Допущения!$B$26 | D11: =-Допущения!$B$27 | E11: =-Допущения!$B$28 | F11: =IF(A11=Допущения!$B$17,Допущения!$B$18*Допущения!$B$22,0) | G11: =SUM(B11:F11) | H11: =H10+G11 | I11: =G11/(1+Допущения!$B$24)^A11
A12: 7 | B12: =Допущения!$B$25 | C12: =-Допущения!$B$26 | D12: =-Допущения!$B$27 | E12: =-Допущения!$B$28 | F12: =IF(A12=Допущения!$B$17,Допущения!$B$18*Допущения!$B$22,0) | G12: =SUM(B12:F12) | H12: =H11+G12 | I12: =G12/(1+Допущения!$B$24)^A12
A13: 8 | B13: =Допущения!$B$25 | C13: =-Допущения!$B$26 | D13: =-Допущения!$B$27 | E13: =-Допущения!$B$28 | F13: =IF(A13=Допущения!$B$17,Допущения!$B$18*Допущения!$B$22,0) | G13: =SUM(B13:F13) | H13: =H12+G13 | I13: =G13/(1+Допущения!$B$24)^A13
A14: 9 | B14: =Допущения!$B$25 | C14: =-Допущения!$B$26 | D14: =-Допущения!$B$27 | E14: =-Допущения!$B$28 | F14: =IF(A14=Допущения!$B$17,Допущения!$B$18*Допущения!$B$22,0) | G14: =SUM(B14:F14) | H14: =H13+G14 | I14: =G14/(1+Допущения!$B$24)^A14
A15: 10 | B15: =Допущения!$B$25 | C15: =-Допущения!$B$26 | D15: =-Допущения!$B$27 | E15: =-Допущения!$B$28 | F15: =IF(A15=Допущения!$B$17,Допущения!$B$18*Допущения!$B$22,0) | G15: =SUM(B15:F15) | H15: =H14+G15 | I15: =G15/(1+Допущения!$B$24)^A15
A16: 11 | B16: =Допущения!$B$25 | C16: =-Допущения!$B$26 | D16: =-Допущения!$B$27 | E16: =-Допущения!$B$28 | F16: =IF(A16=Допущения!$B$17,Допущения!$B$18*Допущения!$B$22,0) | G16: =SUM(B16:F16) | H16: =H15+G16 | I16: =G16/(1+Допущения!$B$24)^A16
A17: 12 | B17: =Допущения!$B$25 | C17: =-Допущения!$B$26 | D17: =-Допущения!$B$27 | E17: =-Допущения!$B$28 | F17: =IF(A17=Допущения!$B$17,Допущения!$B$18*Допущения!$B$22,0) | G17: =SUM(B17:F17) | H17: =H16+G17 | I17: =G17/(1+Допущения!$B$24)^A17
... A41: 36 | B41: =Допущения!$B$25 | C41: =-Допущения!$B$26 | D41: =-Допущения!$B$27 | E41: =-Допущения!$B$28 | F41: =IF(A41=Допущения!$B$17,Допущения!$B$18*Допущения!$B$22,0) | G41: =SUM(B41:F41) | H41: =H40+G41 | I41: =G41/(1+Допущения!$B$24)^A41

Sheet Чувствительность
A1: Срок окупаемости (мес.) при разной цене подписки и стоимости сборки
A2: По строкам — цена подписки, по столбцам — изменение стоимости сборки относительно сегодняшней (сценарии цен на память). Остальные допущения — с листа «Допущения».
A4: Цена \ Сборка | B4: -0.2 | C4: -0.1 | D4: 0 | E4: 0.1 | F4: 0.2 | G4: 0.3
A5: 3990 | B5: =IFERROR(IF(($A5*(1-Допущения!$B$9)*(1-Допущения!$B$13-Допущения!$B$14)-Допущения!$B$5*(1+B$4)*(1-Допущения!$B$6)*(Допущения!$B$15+Допущения!$B$16)/12-Допущения!$B$28)>0,(Допущения!$B$5*(1+B$4)*(1-Допущения!$B$6)+Допущения!$B$7)/($A5*(1-Допущения!$B$9)*(1-Допущения!$B$13-Допущения!$B$14)-Допущения!$B$5*(1+B$4)*(1-Допущения!$B$6)*(Допущения!$B$15+Допущения!$B$16)/12-Допущения!$B$28),"—"),"—") | C5: =IFERROR(IF(($A5*(1-Допущения!$B$9)*(1-Допущения!$B$13-Допущения!$B$14)-Допущения!$B$5*(1+C$4)*(1-Допущения!$B$6)*(Допущения!$B$15+Допущения!$B$16)/12-Допущения!$B$28)>0,(Допущения!$B$5*(1+C$4)*(1-Допущения!$B$6)+Допущения!$B$7)/($A5*(1-Допущения!$B$9)*(1-Допущения!$B$13-Допущения!$B$14)-Допущения!$B$5*(1+C$4)*(1-Допущения!$B$6)*(Допущения!$B$15+Допущения!$B$16)/12-Допущения!$B$28),"—"),"—") | D5: =IFERROR(IF(($A5*(1-Допущения!$B$9)*(1-Допущения!$B$13-Допущения!$B$14)-Допущения!$B$5*(1+D$4)*(1-Допущения!$B$6)*(Допущения!$B$15+Допущения!$B$16)/12-Допущения!$B$28)>0,(Допущения!$B$5*(1+D$4)*(1-Допущения!$B$6)+Допущения!$B$7)/($A5*(1-Допущения!$B$9)*(1-Допущения!$B$13-Допущения!$B$14)-Допущения!$B$5*(1+D$4)*(1-Допущения!$B$6)*(Допущения!$B$15+Допущения!$B$16)/12-Допущения!$B$28),"—"),"—") | E5: =IFERROR(IF(($A5*(1-Допущения!$B$9)*(1-Допущения!$B$13-Допущения!$B$14)-Допущения!$B$5*(1+E$4)*(1-Допущения!$B$6)*(Допущения!$B$15+Допущения!$B$16)/12-Допущения!$B$28)>0,(Допущения!$B$5*(1+E$4)*(1-Допущения!$B$6)+Допущения!$B$7)/($A5*(1-Допущения!$B$9)*(1-Допущения!$B$13-Допущения!$B$14)-Допущения!$B$5*(1+E$4)*(1-Допущения!$B$6)*(Допущения!$B$15+Допущения!$B$16)/12-Допущения!$B$28),"—"),"—") | F5: =IFERROR(IF(($A5*(1-Допущения!$B$9)*(1-Допущения!$B$13-Допущения!$B$14)-Допущения!$B$5*(1+F$4)*(1-Допущения!$B$6)*(Допущения!$B$15+Допущения!$B$16)/12-Допущения!$B$28)>0,(Допущения!$B$5*(1+F$4)*(1-Допущения!$B$6)+Допущения!$B$7)/($A5*(1-Допущения!$B$9)*(1-Допущения!$B$13-Допущения!$B$14)-Допущения!$B$5*(1+F$4)*(1-Допущения!$B$6)*(Допущения!$B$15+Допущения!$B$16)/12-Допущения!$B$28),"—"),"—") | G5: =IFERROR(IF(($A5*(1-Допущения!$B$9)*(1-Допущения!$B$13-Допущения!$B$14)-Допущения!$B$5*(1+G$4)*(1-Допущения!$B$6)*(Допущения!$B$15+Допущения!$B$16)/12-Допущения!$B$28)>0,(Допущения!$B$5*(1+G$4)*(1-Допущения!$B$6)+Допущения!$B$7)/($A5*(1-Допущения!$B$9)*(1-Допущения!$B$13-Допущения!$B$14)-Допущения!$B$5*(1+G$4)*(1-Допущения!$B$6)*(Допущения!$B$15+Допущения!$B$16)/12-Допущения!$B$28),"—"),"—")
A6: 4490 | B6: =IFERROR(IF(($A6*(1-Допущения!$B$9)*(1-Допущения!$B$13-Допущения!$B$14)-Допущения!$B$5*(1+B$4)*(1-Допущения!$B$6)*(Допущения!$B$15+Допущения!$B$16)/12-Допущения!$B$28)>0,(Допущения!$B$5*(1+B$4)*(1-Допущения!$B$6)+Допущения!$B$7)/($A6*(1-Допущения!$B$9)*(1-Допущения!$B$13-Допущения!$B$14)-Допущения!$B$5*(1+B$4)*(1-Допущения!$B$6)*(Допущения!$B$15+Допущения!$B$16)/12-Допущения!$B$28),"—"),"—") | C6: =IFERROR(IF(($A6*(1-Допущения!$B$9)*(1-Допущения!$B$13-Допущения!$B$14)-Допущения!$B$5*(1+C$4)*(1-Допущения!$B$6)*(Допущения!$B$15+Допущения!$B$16)/12-Допущения!$B$28)>0,(Допущения!$B$5*(1+C$4)*(1-Допущения!$B$6)+Допущения!$B$7)/($A6*(1-Допущения!$B$9)*(1-Допущения!$B$13-Допущения!$B$14)-Допущения!$B$5*(1+C$4)*(1-Допущения!$B$6)*(Допущения!$B$15+Допущения!$B$16)/12-Допущения!$B$28),"—"),"—") | D6: =IFERROR(IF(($A6*(1-Допущения!$B$9)*(1-Допущения!$B$13-Допущения!$B$14)-Допущения!$B$5*(1+D$4)*(1-Допущения!$B$6)*(Допущения!$B$15+Допущения!$B$16)/12-Допущения!$B$28)>0,(Допущения!$B$5*(1+D$4)*(1-Допущения!$B$6)+Допущения!$B$7)/($A6*(1-Допущения!$B$9)*(1-Допущения!$B$13-Допущения!$B$14)-Допущения!$B$5*(1+D$4)*(1-Допущения!$B$6)*(Допущения!$B$15+Допущения!$B$16)/12-Допущения!$B$28),"—"),"—") | E6: =IFERROR(IF(($A6*(1-Допущения!$B$9)*(1-Допущения!$B$13-Допущения!$B$14)-Допущения!$B$5*(1+E$4)*(1-Допущения!$B$6)*(Допущения!$B$15+Допущения!$B$16)/12-Допущения!$B$28)>0,(Допущения!$B$5*(1+E$4)*(1-Допущения!$B$6)+Допущения!$B$7)/($A6*(1-Допущения!$B$9)*(1-Допущения!$B$13-Допущения!$B$14)-Допущения!$B$5*(1+E$4)*(1-Допущения!$B$6)*(Допущения!$B$15+Допущения!$B$16)/12-Допущения!$B$28),"—"),"—") | F6: =IFERROR(IF(($A6*(1-Допущения!$B$9)*(1-Допущения!$B$13-Допущения!$B$14)-Допущения!$B$5*(1+F$4)*(1-Допущения!$B$6)*(Допущения!$B$15+Допущения!$B$16)/12-Допущения!$B$28)>0,(Допущения!$B$5*(1+F$4)*(1-Допущения!$B$6)+Допущения!$B$7)/($A6*(1-Допущения!$B$9)*(1-Допущения!$B$13-Допущения!$B$14)-Допущения!$B$5*(1+F$4)*(1-Допущения!$B$6)*(Допущения!$B$15+Допущения!$B$16)/12-Допущения!$B$28),"—"),"—") | G6: =IFERROR(IF(($A6*(1-Допущения!$B$9)*(1-Допущения!$B$13-Допущения!$B$14)-Допущения!$B$5*(1+G$4)*(1-Допущения!$B$6)*(Допущения!$B$15+Допущения!$B$16)/12-Допущения!$B$28)>0,(Допущения!$B$5*(1+G$4)*(1-Допущения!$B$6)+Допущения!$B$7)/($A6*(1-Допущения!$B$9)*(1-Допущения!$B$13-Допущения!$B$14)-Допущения!$B$5*(1+G$4)*(1-Допущения!$B$6)*(Допущения!$B$15+Допущения!$B$16)/12-Допущения!$B$28),"—"),"—")
A7: 4990 | B7: =IFERROR(IF(($A7*(1-Допущения!$B$9)*(1-Допущения!$B$13-Допущения!$B$14)-Допущения!$B$5*(1+B$4)*(1-Допущения!$B$6)*(Допущения!$B$15+Допущения!$B$16)/12-Допущения!$B$28)>0,(Допущения!$B$5*(1+B$4)*(1-Допущения!$B$6)+Допущения!$B$7)/($A7*(1-Допущения!$B$9)*(1-Допущения!$B$13-Допущения!$B$14)-Допущения!$B$5*(1+B$4)*(1-Допущения!$B$6)*(Допущения!$B$15+Допущения!$B$16)/12-Допущения!$B$28),"—"),"—") | C7: =IFERROR(IF(($A7*(1-Допущения!$B$9)*(1-Допущения!$B$13-Допущения!$B$14)-Допущения!$B$5*(1+C$4)*(1-Допущения!$B$6)*(Допущения!$B$15+Допущения!$B$16)/12-Допущения!$B$28)>0,(Допущения!$B$5*(1+C$4)*(1-Допущения!$B$6)+Допущения!$B$7)/($A7*(1-Допущения!$B$9)*(1-Допущения!$B$13-Допущения!$B$14)-Допущения!$B$5*(1+C$4)*(1-Допущения!$B$6)*(Допущения!$B$15+Допущения!$B$16)/12-Допущения!$B$28),"—"),"—") | D7: =IFERROR(IF(($A7*(1-Допущения!$B$9)*(1-Допущения!$B$13-Допущения!$B$14)-Допущения!$B$5*(1+D$4)*(1-Допущения!$B$6)*(Допущения!$B$15+Допущения!$B$16)/12-Допущения!$B$28)>0,(Допущения!$B$5*(1+D$4)*(1-Допущения!$B$6)+Допущения!$B$7)/($A7*(1-Допущения!$B$9)*(1-Допущения!$B$13-Допущения!$B$14)-Допущения!$B$5*(1+D$4)*(1-Допущения!$B$6)*(Допущения!$B$15+Допущения!$B$16)/12-Допущения!$B$28),"—"),"—") | E7: =IFERROR(IF(($A7*(1-Допущения!$B$9)*(1-Допущения!$B$13-Допущения!$B$14)-Допущения!$B$5*(1+E$4)*(1-Допущения!$B$6)*(Допущения!$B$15+Допущения!$B$16)/12-Допущения!$B$28)>0,(Допущения!$B$5*(1+E$4)*(1-Допущения!$B$6)+Допущения!$B$7)/($A7*(1-Допущения!$B$9)*(1-Допущения!$B$13-Допущения!$B$14)-Допущения!$B$5*(1+E$4)*(1-Допущения!$B$6)*(Допущения!$B$15+Допущения!$B$16)/12-Допущения!$B$28),"—"),"—") | F7: =IFERROR(IF(($A7*(1-Допущения!$B$9)*(1-Допущения!$B$13-Допущения!$B$14)-Допущения!$B$5*(1+F$4)*(1-Допущения!$B$6)*(Допущения!$B$15+Допущения!$B$16)/12-Допущения!$B$28)>0,(Допущения!$B$5*(1+F$4)*(1-Допущения!$B$6)+Допущения!$B$7)/($A7*(1-Допущения!$B$9)*(1-Допущения!$B$13-Допущения!$B$14)-Допущения!$B$5*(1+F$4)*(1-Допущения!$B$6)*(Допущения!$B$15+Допущения!$B$16)/12-Допущения!$B$28),"—"),"—") | G7: =IFERROR(IF(($A7*(1-Допущения!$B$9)*(1-Допущения!$B$13-Допущения!$B$14)-Допущения!$B$5*(1+G$4)*(1-Допущения!$B$6)*(Допущения!$B$15+Допущения!$B$16)/12-Допущения!$B$28)>0,(Допущения!$B$5*(1+G$4)*(1-Допущения!$B$6)+Допущения!$B$7)/($A7*(1-Допущения!$B$9)*(1-Допущения!$B$13-Допущения!$B$14)-Допущения!$B$5*(1+G$4)*(1-Допущения!$B$6)*(Допущения!$B$15+Допущения!$B$16)/12-Допущения!$B$28),"—"),"—")
A8: 5490 | B8: =IFERROR(IF(($A8*(1-Допущения!$B$9)*(1-Допущения!$B$13-Допущения!$B$14)-Допущения!$B$5*(1+B$4)*(1-Допущения!$B$6)*(Допущения!$B$15+Допущения!$B$16)/12-Допущения!$B$28)>0,(Допущения!$B$5*(1+B$4)*(1-Допущения!$B$6)+Допущения!$B$7)/($A8*(1-Допущения!$B$9)*(1-Допущения!$B$13-Допущения!$B$14)-Допущения!$B$5*(1+B$4)*(1-Допущения!$B$6)*(Допущения!$B$15+Допущения!$B$16)/12-Допущения!$B$28),"—"),"—") | C8: =IFERROR(IF(($A8*(1-Допущения!$B$9)*(1-Допущения!$B$13-Допущения!$B$14)-Допущения!$B$5*(1+C$4)*(1-Допущения!$B$6)*(Допущения!$B$15+Допущения!$B$16)/12-Допущения!$B$28)>0,(Допущения!$B$5*(1+C$4)*(1-Допущения!$B$6)+Допущения!$B$7)/($A8*(1-Допущения!$B$9)*(1-Допущения!$B$13-Допущения!$B$14)-Допущения!$B$5*(1+C$4)*(1-Допущения!$B$6)*(Допущения!$B$15+Допущения!$B$16)/12-Допущения!$B$28),"—"),"—") | D8: =IFERROR(IF(($A8*(1-Допущения!$B$9)*(1-Допущения!$B$13-Допущения!$B$14)-Допущения!$B$5*(1+D$4)*(1-Допущения!$B$6)*(Допущения!$B$15+Допущения!$B$16)/12-Допущения!$B$28)>0,(Допущения!$B$5*(1+D$4)*(1-Допущения!$B$6)+Допущения!$B$7)/($A8*(1-Допущения!$B$9)*(1-Допущения!$B$13-Допущения!$B$14)-Допущения!$B$5*(1+D$4)*(1-Допущения!$B$6)*(Допущения!$B$15+Допущения!$B$16)/12-Допущения!$B$28),"—"),"—") | E8: =IFERROR(IF(($A8*(1-Допущения!$B$9)*(1-Допущения!$B$13-Допущения!$B$14)-Допущения!$B$5*(1+E$4)*(1-Допущения!$B$6)*(Допущения!$B$15+Допущения!$B$16)/12-Допущения!$B$28)>0,(Допущения!$B$5*(1+E$4)*(1-Допущения!$B$6)+Допущения!$B$7)/($A8*(1-Допущения!$B$9)*(1-Допущения!$B$13-Допущения!$B$14)-Допущения!$B$5*(1+E$4)*(1-Допущения!$B$6)*(Допущения!$B$15+Допущения!$B$16)/12-Допущения!$B$28),"—"),"—") | F8: =IFERROR(IF(($A8*(1-Допущения!$B$9)*(1-Допущения!$B$13-Допущения!$B$14)-Допущения!$B$5*(1+F$4)*(1-Допущения!$B$6)*(Допущения!$B$15+Допущения!$B$16)/12-Допущения!$B$28)>0,(Допущения!$B$5*(1+F$4)*(1-Допущения!$B$6)+Допущения!$B$7)/($A8*(1-Допущения!$B$9)*(1-Допущения!$B$13-Допущения!$B$14)-Допущения!$B$5*(1+F$4)*(1-Допущения!$B$6)*(Допущения!$B$15+Допущения!$B$16)/12-Допущения!$B$28),"—"),"—") | G8: =IFERROR(IF(($A8*(1-Допущения!$B$9)*(1-Допущения!$B$13-Допущения!$B$14)-Допущения!$B$5*(1+G$4)*(1-Допущения!$B$6)*(Допущения!$B$15+Допущения!$B$16)/12-Допущения!$B$28)>0,(Допущения!$B$5*(1+G$4)*(1-Допущения!$B$6)+Допущения!$B$7)/($A8*(1-Допущения!$B$9)*(1-Допущения!$B$13-Допущения!$B$14)-Допущения!$B$5*(1+G$4)*(1-Допущения!$B$6)*(Допущения!$B$15+Допущения!$B$16)/12-Допущения!$B$28),"—"),"—")
A9: 5990 | B9: =IFERROR(IF(($A9*(1-Допущения!$B$9)*(1-Допущения!$B$13-Допущения!$B$14)-Допущения!$B$5*(1+B$4)*(1-Допущения!$B$6)*(Допущения!$B$15+Допущения!$B$16)/12-Допущения!$B$28)>0,(Допущения!$B$5*(1+B$4)*(1-Допущения!$B$6)+Допущения!$B$7)/($A9*(1-Допущения!$B$9)*(1-Допущения!$B$13-Допущения!$B$14)-Допущения!$B$5*(1+B$4)*(1-Допущения!$B$6)*(Допущения!$B$15+Допущения!$B$16)/12-Допущения!$B$28),"—"),"—") | C9: =IFERROR(IF(($A9*(1-Допущения!$B$9)*(1-Допущения!$B$13-Допущения!$B$14)-Допущения!$B$5*(1+C$4)*(1-Допущения!$B$6)*(Допущения!$B$15+Допущения!$B$16)/12-Допущения!$B$28)>0,(Допущения!$B$5*(1+C$4)*(1-Допущения!$B$6)+Допущения!$B$7)/($A9*(1-Допущения!$B$9)*(1-Допущения!$B$13-Допущения!$B$14)-Допущения!$B$5*(1+C$4)*(1-Допущения!$B$6)*(Допущения!$B$15+Допущения!$B$16)/12-Допущения!$B$28),"—"),"—") | D9: =IFERROR(IF(($A9*(1-Допущения!$B$9)*(1-Допущения!$B$13-Допущения!$B$14)-Допущения!$B$5*(1+D$4)*(1-Допущения!$B$6)*(Допущения!$B$15+Допущения!$B$16)/12-Допущения!$B$28)>0,(Допущения!$B$5*(1+D$4)*(1-Допущения!$B$6)+Допущения!$B$7)/($A9*(1-Допущения!$B$9)*(1-Допущения!$B$13-Допущения!$B$14)-Допущения!$B$5*(1+D$4)*(1-Допущения!$B$6)*(Допущения!$B$15+Допущения!$B$16)/12-Допущения!$B$28),"—"),"—") | E9: =IFERROR(IF(($A9*(1-Допущения!$B$9)*(1-Допущения!$B$13-Допущения!$B$14)-Допущения!$B$5*(1+E$4)*(1-Допущения!$B$6)*(Допущения!$B$15+Допущения!$B$16)/12-Допущения!$B$28)>0,(Допущения!$B$5*(1+E$4)*(1-Допущения!$B$6)+Допущения!$B$7)/($A9*(1-Допущения!$B$9)*(1-Допущения!$B$13-Допущения!$B$14)-Допущения!$B$5*(1+E$4)*(1-Допущения!$B$6)*(Допущения!$B$15+Допущения!$B$16)/12-Допущения!$B$28),"—"),"—") | F9: =IFERROR(IF(($A9*(1-Допущения!$B$9)*(1-Допущения!$B$13-Допущения!$B$14)-Допущения!$B$5*(1+F$4)*(1-Допущения!$B$6)*(Допущения!$B$15+Допущения!$B$16)/12-Допущения!$B$28)>0,(Допущения!$B$5*(1+F$4)*(1-Допущения!$B$6)+Допущения!$B$7)/($A9*(1-Допущения!$B$9)*(1-Допущения!$B$13-Допущения!$B$14)-Допущения!$B$5*(1+F$4)*(1-Допущения!$B$6)*(Допущения!$B$15+Допущения!$B$16)/12-Допущения!$B$28),"—"),"—") | G9: =IFERROR(IF(($A9*(1-Допущения!$B$9)*(1-Допущения!$B$13-Допущения!$B$14)-Допущения!$B$5*(1+G$4)*(1-Допущения!$B$6)*(Допущения!$B$15+Допущения!$B$16)/12-Допущения!$B$28)>0,(Допущения!$B$5*(1+G$4)*(1-Допущения!$B$6)+Допущения!$B$7)/($A9*(1-Допущения!$B$9)*(1-Допущения!$B$13-Допущения!$B$14)-Допущения!$B$5*(1+G$4)*(1-Допущения!$B$6)*(Допущения!$B$15+Допущения!$B$16)/12-Допущения!$B$28),"—"),"—")
A10: 6990 | B10: =IFERROR(IF(($A10*(1-Допущения!$B$9)*(1-Допущения!$B$13-Допущения!$B$14)-Допущения!$B$5*(1+B$4)*(1-Допущения!$B$6)*(Допущения!$B$15+Допущения!$B$16)/12-Допущения!$B$28)>0,(Допущения!$B$5*(1+B$4)*(1-Допущения!$B$6)+Допущения!$B$7)/($A10*(1-Допущения!$B$9)*(1-Допущения!$B$13-Допущения!$B$14)-Допущения!$B$5*(1+B$4)*(1-Допущения!$B$6)*(Допущения!$B$15+Допущения!$B$16)/12-Допущения!$B$28),"—"),"—") | C10: =IFERROR(IF(($A10*(1-Допущения!$B$9)*(1-Допущения!$B$13-Допущения!$B$14)-Допущения!$B$5*(1+C$4)*(1-Допущения!$B$6)*(Допущения!$B$15+Допущения!$B$16)/12-Допущения!$B$28)>0,(Допущения!$B$5*(1+C$4)*(1-Допущения!$B$6)+Допущения!$B$7)/($A10*(1-Допущения!$B$9)*(1-Допущения!$B$13-Допущения!$B$14)-Допущения!$B$5*(1+C$4)*(1-Допущения!$B$6)*(Допущения!$B$15+Допущения!$B$16)/12-Допущения!$B$28),"—"),"—") | D10: =IFERROR(IF(($A10*(1-Допущения!$B$9)*(1-Допущения!$B$13-Допущения!$B$14)-Допущения!$B$5*(1+D$4)*(1-Допущения!$B$6)*(Допущения!$B$15+Допущения!$B$16)/12-Допущения!$B$28)>0,(Допущения!$B$5*(1+D$4)*(1-Допущения!$B$6)+Допущения!$B$7)/($A10*(1-Допущения!$B$9)*(1-Допущения!$B$13-Допущения!$B$14)-Допущения!$B$5*(1+D$4)*(1-Допущения!$B$6)*(Допущения!$B$15+Допущения!$B$16)/12-Допущения!$B$28),"—"),"—") | E10: =IFERROR(IF(($A10*(1-Допущения!$B$9)*(1-Допущения!$B$13-Допущения!$B$14)-Допущения!$B$5*(1+E$4)*(1-Допущения!$B$6)*(Допущения!$B$15+Допущения!$B$16)/12-Допущения!$B$28)>0,(Допущения!$B$5*(1+E$4)*(1-Допущения!$B$6)+Допущения!$B$7)/($A10*(1-Допущения!$B$9)*(1-Допущения!$B$13-Допущения!$B$14)-Допущения!$B$5*(1+E$4)*(1-Допущения!$B$6)*(Допущения!$B$15+Допущения!$B$16)/12-Допущения!$B$28),"—"),"—") | F10: =IFERROR(IF(($A10*(1-Допущения!$B$9)*(1-Допущения!$B$13-Допущения!$B$14)-Допущения!$B$5*(1+F$4)*(1-Допущения!$B$6)*(Допущения!$B$15+Допущения!$B$16)/12-Допущения!$B$28)>0,(Допущения!$B$5*(1+F$4)*(1-Допущения!$B$6)+Допущения!$B$7)/($A10*(1-Допущения!$B$9)*(1-Допущения!$B$13-Допущения!$B$14)-Допущения!$B$5*(1+F$4)*(1-Допущения!$B$6)*(Допущения!$B$15+Допущения!$B$16)/12-Допущения!$B$28),"—"),"—") | G10: =IFERROR(IF(($A10*(1-Допущения!$B$9)*(1-Допущения!$B$13-Допущения!$B$14)-Допущения!$B$5*(1+G$4)*(1-Допущения!$B$6)*(Допущения!$B$15+Допущения!$B$16)/12-Допущения!$B$28)>0,(Допущения!$B$5*(1+G$4)*(1-Допущения!$B$6)+Допущения!$B$7)/($A10*(1-Допущения!$B$9)*(1-Допущения!$B$13-Допущения!$B$14)-Допущения!$B$5*(1+G$4)*(1-Допущения!$B$6)*(Допущения!$B$15+Допущения!$B$16)/12-Допущения!$B$28),"—"),"—")
A12: Как читать: при сегодняшних ценах и подписке 4 990 ₽ ПК окупается за значение в центре. Если память подешевеет на 20%, срок сокращается; если подорожает ещё на 30% — растёт.

Sheet Альтернативы
A1: Что дешевле для геймера: купить, ходить в клуб, облако или подписка
A2: Сравнение расходов геймера за период. Часы игры в месяц — входной параметр.
A4: Часов игры в месяц | B4: 60
A5: Ставка по рассрочке / кредиту | B5: 0.25 | C5: Допущение: рассрочка с переплатой, типично для потребкредита при ставке ЦБ 14%
A6: Срок рассрочки, мес | B6: 12
A7: Клуб: средние траты гостя в месяц | B7: 1570 | C7: АРКИ, IV кв. 2025: медианная выручка на гостя 1 570 ₽ (Москва и СПб ~1 900 ₽)
A8: Облако (МТС Fog Play), ₽ за час | B8: 24 | C8: fogplay.mts.ru: от 24 ₽/час, поминутная оплата
A10: Вариант | B10: Платёж в месяц | C10: За 12 мес | D10: За 24 мес | E10: Комментарий
A11: Купить сразу в DNS | B11: =0 | C11: =Допущения!$B$5 | D11: =Допущения!$B$5 | E11: Нужна вся сумма сразу
A12: Купить в кредит | B12: =PMT($B$5/12,$B$6,-Допущения!$B$5) | C12: =B12*$B$6 | D12: =B12*$B$6 | E12: Аннуитет; после выплаты ПК ваш
A13: Компьютерный клуб | B13: =$B$7 | C13: =B13*12 | D13: =B13*24 | E13: Нет ПК дома, ограничено часами
A14: Облачный гейминг | B14: =$B$4*$B$8 | C14: =B14*12 | D14: =B14*24 | E14: Нужен быстрый интернет, задержки
A15: Подписка на ПК | B15: =Допущения!$B$8 | C15: =B15*12 | D15: =B15*24 | E15: ПК дома, без первого взноса, можно вернуть

Sheet Рынок
A1: Оценка рынка: TAM / SAM / SOM
A2: Сверху вниз. Синие ячейки — источники или допущения, их можно уточнять.
A4: Шаг | B4: Значение | C4: Источник / логика
A5: Аудитория видеоигр в России, чел. | B5: 108000000 | C5: РВИ, ИФСИ, НАФИ (2025): 106–110 млн, берём середину
A6: Доля считающих себя геймерами | B6: 0.17 | C6: Там же: каждый шестой играющий (17%)
A7: Геймеры, чел. | B7: =B5*B6
A8: Доля играющих в основном на ПК | B8: 0.5 | C8: Допущение; опросы дают 50–60%
A9: Нет подходящего игрового ПК или пора менять | B9: 0.3 | C9: Допущение; проверить опросом
A10: TAM, чел. | B10: =B7*B8*B9 | C10: Все, кому нужен новый игровой ПК
A11: TAM, ₽ в год | B11: =B10*Допущения!$B$8*12 | C11: Если бы все платили за подписку
A12: Доля в городах-миллионниках | B12: 0.24 | C12: Росстат: ~35 млн из 146 млн жителей
A13: Готовы платить за подписку, а не покупать | B13: 0.1 | C13: Допущение; проверить опросом и пилотом
A14: SAM, чел. | B14: =B10*B12*B13 | C14: Реально достижимый сегмент
A15: SAM, ₽ в год | B15: =B14*Допущения!$B$8*12
A16: Доля SAM через 3 года | B16: 0.05 | C16: Цель, допущение
A17: SOM, подписчиков | B17: =B14*B16
A18: SOM, ₽ в год | B18: =B17*Допущения!$B$8*12
A19: Нужно вложить в парк ПК | B19: =B17*Допущения!$B$23*(1+Допущения!$B$9) | C19: Парк с запасом на простой
A20: Проверка: гостей компьютерных клубов в месяц | B20: 1000000 | C20: АРКИ: >1 млн уникальных гостей в месяц, пик ~1,2 млн (ноябрь 2025)

Sheet Источники
A1: Источники
A3: Что | B3: Источник | C3: Ссылка
A4: Цены DNS | B4: Собственный сбор, src/collect_local.py, 24.09.2026
A5: Цены Регард и история | B5: Собственный сбор, src/collect_regard.py, src/collect_history.py (Wayback Machine)
A6: Контрактные цены DRAM | B6: TrendForce, пресс-релизы 05.01.2026, 31.03.2026, 01.06.2026, 03.07.2026 | C6: https://www.trendforce.com/presscenter/news/20260601-13070.html
A7: Аудитория видеоигр | B7: РВИ, ИФСИ, НАФИ, исследование «Гейминг в России» | C7: https://creative.hse.ru/news/6359
A8: Компьютерные клубы | B8: АРКИ, барометр за IV кв. 2025 (CNews, 30.01.2026) | C8: https://www.cnews.ru/news/line/2026-01-30_rynok_kompyuternyh_klubov
A9: Аренда игровых ПК | B9: Aura-Rent, прайс на аренду игровых ПК, Москва | C9: https://msk.aura-rent.ru/arenda-igrovyh-kompjuterov/
A10: Облачный гейминг | B10: МТС Fog Play, тарифы | C10: https://fogplay.mts.ru/
A11: Ключевая ставка | B11: Банк России, 14% на 23.09.2026 | C11: https://www.cbr.ru/hd_base/KeyRate/
